rtshell/__init__.py
rtshell/actions.py
rtshell/comp_mgmt.py
rtshell/fmt.py
rtshell/gen_comp.py
rtshell/ilog.py
rtshell/modmgr.py
rtshell/option_store.py
rtshell/path.py
rtshell/plan.py
rtshell/port_types.py
rtshell/post_install.py
rtshell/rtact.py
rtshell/rtcat.py
rtshell/rtcheck.py
rtshell/rtcomp.py
rtshell/rtcon.py
rtshell/rtconf.py
rtshell/rtcryo.py
rtshell/rtcwd.py
rtshell/rtdeact.py
rtshell/rtdel.py
rtshell/rtdis.py
rtshell/rtdoc.py
rtshell/rtexit.py
rtshell/rtfind.py
rtshell/rtfsm.py
rtshell/rtinject.py
rtshell/rtinject_comp.py
rtshell/rtlog.py
rtshell/rtlog_comps.py
rtshell/rtls.py
rtshell/rtmgr.py
rtshell/rtprint.py
rtshell/rtprint_comp.py
rtshell/rtpwd.py
rtshell/rtreset.py
rtshell/rtresurrect.py
rtshell/rts_exceptions.py
rtshell/rtstart.py
rtshell/rtstodot.py
rtshell/rtstop.py
rtshell/rtteardown.py
rtshell/rtvlog.py
rtshell/rtwatch.py
rtshell/simpkl_log.py
rtshell/state_control_base.py
rtshell/text_log.py
rtshell/data/__init__.py
rtshell/data/bash_completion
rtshell/data/rtcwd.bat
rtshell/data/shell_support
rtshell/data/doc/html/en/rtact.html
rtshell/data/doc/html/en/rtcat.html
rtshell/data/doc/html/en/rtcheck.html
rtshell/data/doc/html/en/rtcomp.html
rtshell/data/doc/html/en/rtcon.html
rtshell/data/doc/html/en/rtconf.html
rtshell/data/doc/html/en/rtcryo.html
rtshell/data/doc/html/en/rtcwd.html
rtshell/data/doc/html/en/rtdeact.html
rtshell/data/doc/html/en/rtdel.html
rtshell/data/doc/html/en/rtdis.html
rtshell/data/doc/html/en/rtdoc.html
rtshell/data/doc/html/en/rtexit.html
rtshell/data/doc/html/en/rtfind.html
rtshell/data/doc/html/en/rtinject.html
rtshell/data/doc/html/en/rtlog.html
rtshell/data/doc/html/en/rtls.html
rtshell/data/doc/html/en/rtmgr.html
rtshell/data/doc/html/en/rtprint.html
rtshell/data/doc/html/en/rtpwd.html
rtshell/data/doc/html/en/rtreset.html
rtshell/data/doc/html/en/rtresurrect.html
rtshell/data/doc/html/en/rtshell.html
rtshell/data/doc/html/en/rtstart.html
rtshell_aist-4.2.9.dist-info/DESCRIPTION.rst
rtshell_aist-4.2.9.dist-info/METADATA
rtshell_aist-4.2.9.dist-info/RECORD
rtshell_aist-4.2.9.dist-info/WHEEL
rtshell_aist-4.2.9.dist-info/entry_points.txt
rtshell_aist-4.2.9.dist-info/metadata.json
rtshell_aist-4.2.9.dist-info/top_level.txt
